tqsdk_zq_history/__init__.py
tqsdk_zq_history-1.0.0.dist-info/METADATA
tqsdk_zq_history-1.0.0.dist-info/WHEEL
tqsdk_zq_history-1.0.0.dist-info/top_level.txt
tqsdk_zq_history-1.0.0.dist-info/RECORD
