Metadata-Version: 2.1
Name: tqsdk-zq-history
Version: 1.0.0
Summary: TianQin SDK - zq_history lib
Home-page: https://www.shinnytech.com/tqsdk
Author: TianQin
Author-email: tianqincn@gmail.com
License: UNKNOWN
Platform: UNKNOWN
Requires-Python: >=3
